badger_config_handler/__init__.py
badger_config_handler/badger_config_handler.py
badger_config_handler-0.3.1.dist-info/LICENSE
badger_config_handler-0.3.1.dist-info/METADATA
badger_config_handler-0.3.1.dist-info/WHEEL
badger_config_handler-0.3.1.dist-info/top_level.txt
badger_config_handler-0.3.1.dist-info/RECORD
